addFabricNode.py
addMgmtProvidedOutOfBandContract.py
addPrivateL3Network.py
addSecurityDomain.py
addUserDomain.py
addVmmDomainAssociation.py
associateL3OutsideNetworkToBD.py
chooseRoleForUser.py
configureInBandEpgDefault.py
configureInterfacePcAndVpc.py
connectEpgContract.py
createAccessPortPolicyGroup.py
createApplication.py
createApplicationEpg.py
createAttachableAccessEntityprofile.py
createBgpRouteReflector.py
createBridgeDomainSubnet.py
createContract.py
createExternalManagementEntityInstance.py
createExternalNetwork.py
createFilter.py
createInterfaceProfile.py
createL3EpgProviderOrConsumerContract.py
createLocalUser.py
createMo.py
createMulticastAddressBlock.py
createNodeManagementAddress.py
createNodes.py
createNodesAndInterfacesProfile.py
createOutOfBandContract.py
createPhysicalDomain.py
createPodPolicyGroup.py
createRadiusProvider.py
createRoutedInterfaceProfile.py
createRoutedOutside.py
createStaticRoute.py
createSubnet.py
createTenant.py
createVcenterController.py
createVcenterCredential.py
createVcenterDomain.py
createVlanPool.py
createVshieldController.py
createVxlanPool.py
selectPodPolicy.py
setAutonomousSystemNumber.py
setDefaultSettingForPrivateNetwork.py
setup.py
apic_python.egg-info/PKG-INFO
apic_python.egg-info/SOURCES.txt
apic_python.egg-info/dependency_links.txt
apic_python.egg-info/top_level.txt