Metadata-Version: 1.0
Name: apic-python
Version: 0.0.1
Summary: This are codes for creating MO in APIC through CLI
Home-page: https://github.com/datacenter/ACI/tree/master/configuration-python
Author: Bon Huang
Author-email: bangyellow@hotmail.com
License: Cisco
Keywords: Create MO in Cisco APIC
Platform: UNKNOWN
